{
    "360": 57944,
    "ab-testing": 57945,
    "add-small": 57946,
    "add": 57947,
    "address-book": 57948,
    "adjust-horizontal-alt": 57949,
    "adjust-horizontal": 57950,
    "adjust-vertical-alt": 57951,
    "adjust-vertical": 57952,
    "airplay": 57953,
    "airpods": 57954,
    "alarm": 57955,
    "alien": 57956,
    "align-bottom": 57957,
    "align-center-horizontal": 57958,
    "align-center-vertical": 57959,
    "align-left": 57960,
    "align-right": 57961,
    "align-text-center": 57962,
    "align-text-justify": 57963,
    "align-text-left": 57964,
    "align-text-right": 57965,
    "align-top": 57966,
    "anchor": 57967,
    "android": 57968,
    "angular": 57969,
    "anja": 57970,
    "anti-clockwise": 57971,
    "apple": 57972,
    "appointments": 57973,
    "archive": 57974,
    "area-chart-alt": 57975,
    "area-chart": 57976,
    "arrow-down-circle": 57977,
    "arrow-down-small": 57978,
    "arrow-down": 57979,
    "arrow-left-circle": 57980,
    "arrow-left-small": 57981,
    "arrow-left": 57982,
    "arrow-right-circle": 57983,
    "arrow-right-small": 57984,
    "arrow-right": 57985,
    "arrow-up-circle": 57986,
    "arrow-up-small": 57987,
    "arrow-up": 57988,
    "arrow": 57989,
    "artboard": 57990,
    "at": 57991,
    "attach": 57992,
    "attachment": 57993,
    "audio-cable": 57994,
    "audio-document": 57995,
    "azure": 57996,
    "backspace": 57997,
    "bag-alt": 57998,
    "bag-minus": 57999,
    "bag-plus": 58000,
    "bag": 58001,
    "bank": 58002,
    "bar-chart": 58003,
    "barcode": 58004,
    "basket-minus": 58005,
    "basket-plus": 58006,
    "basket": 58007,
    "bath": 58008,
    "battery-0": 58009,
    "battery-1": 58010,
    "battery-2": 58011,
    "battery-3": 58012,
    "battery-4": 58013,
    "battery-5": 58014,
    "battery-charge": 58015,
    "bed-double": 58016,
    "bed-single": 58017,
    "behance": 58018,
    "bell": 58019,
    "bin": 58020,
    "bitbucket": 58021,
    "bitcoin": 58022,
    "bluetooth": 58023,
    "bold": 58024,
    "book": 58025,
    "bookmark": 58026,
    "border-all": 58027,
    "border-bottom": 58028,
    "border-horizontal": 58029,
    "border-inner": 58030,
    "border-left": 58031,
    "border-none": 58032,
    "border-outer": 58033,
    "border-radius": 58034,
    "border-right": 58035,
    "border-top": 58036,
    "border-vertical": 58037,
    "bottom-left": 58038,
    "bottom-right": 58039,
    "box": 58040,
    "bracket": 58041,
    "briefcase-alt": 58042,
    "briefcase": 58043,
    "brush": 58044,
    "bug": 58045,
    "building": 58046,
    "bulb-off": 58047,
    "bulb-on": 58048,
    "button": 58049,
    "c-sharp": 58050,
    "c": 58051,
    "calculator": 58052,
    "calendar-minus": 58053,
    "calendar-no-access": 58054,
    "calendar-plus": 58055,
    "calendar-tick": 58056,
    "calendar-x": 58057,
    "calendar": 58058,
    "camera": 58059,
    "candle-chart": 58060,
    "car": 58061,
    "caret-vertical-circle": 58062,
    "caret-vertical-small": 58063,
    "caret-vertical": 58064,
    "cart-minus": 58065,
    "cart-plus": 58066,
    "cart": 58067,
    "certificate": 58068,
    "chat-typing-alt": 58069,
    "chat-typing": 58070,
    "chat": 58071,
    "chatbot": 58072,
    "chrome": 58073,
    "church": 58074,
    "circle": 58075,
    "clipboard-minus": 58076,
    "clipboard-no-access": 58077,
    "clipboard-plus": 58078,
    "clipboard-tick": 58079,
    "clipboard-x": 58080,
    "clipboard": 58081,
    "clock": 58082,
    "clockwise": 58083,
    "code": 58084,
    "codepen": 58085,
    "cog": 58086,
    "compass": 58087,
    "computer": 58088,
    "contact": 58089,
    "contract": 58090,
    "cost-estimate": 58091,
    "cplusplus": 58092,
    "credit-card": 58093,
    "crop": 58094,
    "css3": 58095,
    "csv": 58096,
    "cup": 58097,
    "curved-connector": 58098,
    "d3": 58099,
    "database": 58100,
    "denied": 58101,
    "deno": 58102,
    "depth-chart": 58103,
    "desklamp": 58104,
    "diamond": 58105,
    "direction": 58106,
    "discord": 58107,
    "discount": 58108,
    "distribute-horizontal": 58109,
    "distribute-vertical": 58110,
    "divider-line": 58111,
    "doc": 58112,
    "docker": 58113,
    "documents": 58114,
    "dollar": 58115,
    "donut-chart": 58116,
    "double-caret-down-circle": 58117,
    "double-caret-down-small": 58118,
    "double-caret-down": 58119,
    "double-caret-left-circle": 58120,
    "double-caret-left-small": 58121,
    "double-caret-left": 58122,
    "double-caret-right-circle": 58123,
    "double-caret-right-small": 58124,
    "double-caret-right": 58125,
    "double-caret-up-circle": 58126,
    "double-caret-up-small": 58127,
    "double-caret-up": 58128,
    "down-circle": 58129,
    "down-small": 58130,
    "down": 58131,
    "download": 58132,
    "drag-horizontal": 58133,
    "drag-vertical": 58134,
    "drag": 58135,
    "dribbble": 58136,
    "drop": 58137,
    "dropper": 58138,
    "edge": 58139,
    "edit-1": 58140,
    "edit-circle": 58141,
    "edit-small": 58142,
    "edit": 58143,
    "elbow-connector": 58144,
    "envelope-open": 58145,
    "envelope": 58146,
    "eps": 58147,
    "eslint": 58148,
    "ethereum": 58149,
    "euro": 58150,
    "exclamation-circle": 58151,
    "exclamation-small": 58152,
    "exclamation": 58153,
    "expand-alt": 58154,
    "expand": 58155,
    "eye-closed": 58156,
    "eye": 58157,
    "face-id": 58158,
    "facebook": 58159,
    "figma": 58160,
    "file-minus": 58161,
    "file-no-access": 58162,
    "file-plus": 58163,
    "file-tick": 58164,
    "file-x": 58165,
    "file": 58166,
    "filter": 58167,
    "fingerprint": 58168,
    "firebase": 58169,
    "flag-alt": 58170,
    "flag": 58171,
    "flip-horizontal": 58172,
    "flip-vertical": 58173,
    "float-center": 58174,
    "float-left": 58175,
    "float-right": 58176,
    "floorplan": 58177,
    "folder-minus": 58178,
    "folder-no-access": 58179,
    "folder-plus": 58180,
    "folder-tick": 58181,
    "folder-x": 58182,
    "folder": 58183,
    "folders": 58184,
    "forward-circle": 58185,
    "forward-small": 58186,
    "forward": 58187,
    "frame": 58188,
    "framer": 58189,
    "game-controller-retro": 58190,
    "game-controller": 58191,
    "gantt-chart": 58192,
    "garage": 58193,
    "gatsbyjs": 58194,
    "gba": 58195,
    "gbc": 58196,
    "ghost": 58197,
    "gif": 58198,
    "gift": 58199,
    "git-branch": 58200,
    "git-commit": 58201,
    "git-compare": 58202,
    "git-fork": 58203,
    "git-merge": 58204,
    "git-pull": 58205,
    "git": 58206,
    "github": 58207,
    "gitlab": 58208,
    "globe-africa": 58209,
    "globe-americas": 58210,
    "globe": 58211,
    "google-ad": 58212,
    "google-drive": 58213,
    "google-play-store": 58214,
    "google-streetview": 58215,
    "google": 58216,
    "graphql": 58217,
    "grid-layout": 58218,
    "hashtag": 58219,
    "hd-screen": 58220,
    "hdmi-cable": 58221,
    "headphones": 58222,
    "headset": 58223,
    "heart-circle": 58224,
    "heart-small": 58225,
    "heart": 58226,
    "hexagon": 58227,
    "history": 58228,
    "home-alt": 58229,
    "home": 58230,
    "hospital": 58231,
    "hourglass": 58232,
    "house": 58233,
    "html5": 58234,
    "id": 58235,
    "imac": 58236,
    "image-alt": 58237,
    "image-document": 58238,
    "image": 58239,
    "in-ear-headphones": 58240,
    "inbox": 58241,
    "indent-decrease": 58242,
    "indent-increase": 58243,
    "info-circle": 58244,
    "info-small": 58245,
    "info": 58246,
    "instagram": 58247,
    "invoice": 58248,
    "italic": 58249,
    "javascript": 58250,
    "joystick": 58251,
    "jpg": 58252,
    "kanban": 58253,
    "key": 58254,
    "keyboard": 58255,
    "lan-cable": 58256,
    "laptop": 58257,
    "laravel": 58258,
    "layers-difference": 58259,
    "layers-intersect": 58260,
    "layers-subtract": 58261,
    "layers-union": 58262,
    "layers": 58263,
    "left-circle": 58264,
    "left-small": 58265,
    "left": 58266,
    "lego": 58267,
    "lifebuoy": 58268,
    "lightning-cable": 58269,
    "line": 58270,
    "link-remove": 58271,
    "link": 58272,
    "linkedin": 58273,
    "linux-alt": 58274,
    "linux": 58275,
    "list-layout": 58276,
    "list-ordered": 58277,
    "list-unordered": 58278,
    "litecoin": 58279,
    "loader": 58280,
    "location": 58281,
    "lock-circle": 58282,
    "lock-small": 58283,
    "lock": 58284,
    "logout": 58285,
    "loop": 58286,
    "magsafe": 58287,
    "markdown": 58288,
    "medium": 58289,
    "menu": 58290,
    "message-minus": 58291,
    "message-no-access": 58292,
    "message-plus": 58293,
    "message-text-alt": 58294,
    "message-text": 58295,
    "message-tick": 58296,
    "message-x": 58297,
    "message": 58298,
    "messenger": 58299,
    "micro-sd-card": 58300,
    "microphone": 58301,
    "minimise-alt": 58302,
    "minimise": 58303,
    "minus-circle": 58304,
    "minus-small": 58305,
    "minus": 58306,
    "mobile": 58307,
    "money-stack": 58308,
    "money": 58309,
    "mongodb": 58310,
    "mood-flat": 58311,
    "mood-frown": 58312,
    "mood-laugh": 58313,
    "mood-sad": 58314,
    "mood-smile": 58315,
    "mood-surprised": 58316,
    "mood-tongue": 58317,
    "moon": 58318,
    "more-horizontal": 58319,
    "more-vertical": 58320,
    "mouse": 58321,
    "mov": 58322,
    "mp3": 58323,
    "mp4": 58324,
    "ms-excel": 58325,
    "ms-powerpoint": 58326,
    "ms-word": 58327,
    "n64": 58328,
    "nes": 58329,
    "netlify": 58330,
    "next-circle": 58331,
    "next-small": 58332,
    "next": 58333,
    "nextjs": 58334,
    "ngc": 58335,
    "nintendo-switch": 58336,
    "nodejs": 58337,
    "note": 58338,
    "npm": 58339,
    "nuxtjs": 58340,
    "omega": 58341,
    "opera": 58342,
    "otp": 58343,
    "page-break": 58344,
    "page-number": 58345,
    "paintbrush": 58346,
    "paintbucket": 58347,
    "paragraph": 58348,
    "password": 58349,
    "patreon": 58350,
    "pause-circle": 58351,
    "pause-small": 58352,
    "pause": 58353,
    "paw": 58354,
    "paws": 58355,
    "paypal": 58356,
    "pdf": 58357,
    "pen": 58358,
    "phone": 58359,
    "phonecall-blocked": 58360,
    "phonecall-receive": 58361,
    "phonecall": 58362,
    "pie-chart-alt": 58363,
    "pie-chart": 58364,
    "pin-alt": 58365,
    "pin": 58366,
    "pinterest": 58367,
    "plant": 58368,
    "play-circle": 58369,
    "play-small": 58370,
    "play": 58371,
    "plug": 58372,
    "plus-circle": 58373,
    "png": 58374,
    "pool": 58375,
    "pound": 58376,
    "power": 58377,
    "ppt": 58378,
    "print": 58379,
    "python": 58380,
    "qr-code": 58381,
    "question-circle": 58382,
    "question-small": 58383,
    "question": 58384,
    "quote": 58385,
    "rand": 58386,
    "react": 58387,
    "receipt": 58388,
    "reddit": 58389,
    "redwoodjs": 58390,
    "refresh-alt": 58391,
    "refresh": 58392,
    "rewind-circle": 58393,
    "rewind-small": 58394,
    "rewind": 58395,
    "right-circle": 58396,
    "right-small": 58397,
    "right": 58398,
    "ripple": 58399,
    "robot": 58400,
    "roller": 58401,
    "rollupjs": 58402,
    "router": 58403,
    "rss": 58404,
    "ruby": 58405,
    "rupee": 58406,
    "rust": 58407,
    "safari": 58408,
    "safe": 58409,
    "save": 58410,
    "scan": 58411,
    "school": 58412,
    "screen-alt-2": 58413,
    "screen-alt": 58414,
    "screen": 58415,
    "scribble": 58416,
    "sd-card": 58417,
    "search-circle": 58418,
    "search-property": 58419,
    "search-small": 58420,
    "search": 58421,
    "section-add": 58422,
    "section-remove": 58423,
    "send-down": 58424,
    "send-left": 58425,
    "send-right": 58426,
    "send-up": 58427,
    "send": 58428,
    "servers": 58429,
    "share": 58430,
    "shield-tick": 58431,
    "shield-x": 58432,
    "shield": 58433,
    "shop": 58434,
    "sign": 58435,
    "signin": 58436,
    "sim": 58437,
    "simohamed": 58438,
    "skull": 58439,
    "skype": 58440,
    "slack": 58441,
    "snapchat": 58442,
    "snes": 58443,
    "sort-alphabetically": 58444,
    "sort-down": 58445,
    "sort-high-to-low": 58446,
    "sort-low-to-high": 58447,
    "sort-reverse-alphabetically": 58448,
    "sort-up": 58449,
    "sound-off": 58450,
    "sound-on": 58451,
    "spotify": 58452,
    "spreadsheet": 58453,
    "square": 58454,
    "stackoverflow": 58455,
    "stamp": 58456,
    "star-circle": 58457,
    "star-small": 58458,
    "star": 58459,
    "stop-circle": 58460,
    "stop-small": 58461,
    "stop": 58462,
    "stopwatch": 58463,
    "strikethrough": 58464,
    "subscript": 58465,
    "sun": 58466,
    "superscript": 58467,
    "svelte": 58468,
    "svg": 58469,
    "table": 58470,
    "tablet": 58471,
    "tag": 58472,
    "tailwind": 58473,
    "target": 58474,
    "telegram": 58475,
    "terminal": 58476,
    "text-document-alt": 58477,
    "text-document": 58478,
    "text": 58479,
    "thumb-down": 58480,
    "thumb-up": 58481,
    "thumbtack": 58482,
    "tick-circle": 58483,
    "tick-small": 58484,
    "tick": 58485,
    "tiktok": 58486,
    "toggle": 58487,
    "top-left": 58488,
    "top-right": 58489,
    "trend-down": 58490,
    "trend-up": 58491,
    "triangle": 58492,
    "trophy": 58493,
    "tv": 58494,
    "twitch": 58495,
    "twitter": 58496,
    "typescript": 58497,
    "underline": 58498,
    "unlock-circle": 58499,
    "unlock-small": 58500,
    "unlock": 58501,
    "up-circle": 58502,
    "up-small": 58503,
    "up": 58504,
    "upload": 58505,
    "usb-cable": 58506,
    "user-circle": 58507,
    "user-minus": 58508,
    "user-plus": 58509,
    "user-square": 58510,
    "user": 58511,
    "users": 58512,
    "vector-document": 58513,
    "venn-diagram": 58514,
    "view-column": 58515,
    "view-grid": 58516,
    "vim": 58517,
    "volume-1": 58518,
    "volume-2": 58519,
    "volume-3": 58520,
    "vr-headset": 58521,
    "vue": 58522,
    "wallet-alt": 58523,
    "wallet": 58524,
    "wan": 58525,
    "wand": 58526,
    "watch": 58527,
    "webpack": 58528,
    "whatsapp": 58529,
    "wifi-full": 58530,
    "wifi-low": 58531,
    "wifi-none": 58532,
    "windows": 58533,
    "wordpress": 58534,
    "x-circle": 58535,
    "x-small": 58536,
    "x": 58537,
    "xls": 58538,
    "yen": 58539,
    "youtube": 58540,
    "zip": 58541,
    "zoom-in": 58542,
    "zoom-out": 58543
}